{
  "passes": {
    "ex01": [
      {
        "user": "urmsandeep-test-01",
        "ts": "2026-04-22T08:32:34.554686+00:00"
      },
      {
        "user": "urmsandeep",
        "ts": "2026-04-22T11:03:19.250215+00:00"
      },
      {
        "user": "Vishnureddy910",
        "ts": "2026-04-22T11:03:19.250215+00:00"
      },
      {
        "user": "Akif-ka",
        "ts": "2026-04-22T11:08:46.230905+00:00"
      },
      {
        "user": "akshay-820",
        "ts": "2026-04-22T11:10:37.118457+00:00"
      },
      {
        "user": "Adithya-Vipin",
        "ts": "2026-04-22T11:14:29.584336+00:00"
      },
      {
        "user": "BKSHEERAJ",
        "ts": "2026-04-22T11:14:29.584336+00:00"
      },
      {
        "user": "chethanataltaje",
        "ts": "2026-04-22T11:29:56.383489+00:00"
      },
      {
        "user": "batulhs",
        "ts": "2026-04-30T11:23:50.878904+00:00"
      }
    ]
  },
  "attempts": {
    "urmsandeep-test-01|ex01": 1,
    "urmsandeep-test-01|ex02": 474,
    "urmsandeep-test-01|ex03": 474,
    "urmsandeep-test-01|ex04": 474,
    "urmsandeep-test-01|ex05": 474,
    "urmsandeep-test-01|ex06": 474,
    "urmsandeep-test-01|ex07": 474,
    "urmsandeep-test-01|ex08": 474,
    "urmsandeep-test-01|ex09": 474,
    "urmsandeep-test-01|ex10": 474,
    "urmsandeep|ex01": 7,
    "urmsandeep|ex02": 474,
    "urmsandeep|ex03": 474,
    "urmsandeep|ex04": 474,
    "urmsandeep|ex05": 474,
    "urmsandeep|ex06": 474,
    "urmsandeep|ex07": 474,
    "urmsandeep|ex08": 474,
    "urmsandeep|ex09": 474,
    "urmsandeep|ex10": 474,
    "afrinmtp|ex01": 470,
    "afrinmtp|ex02": 470,
    "afrinmtp|ex03": 470,
    "afrinmtp|ex04": 470,
    "afrinmtp|ex05": 470,
    "afrinmtp|ex06": 470,
    "afrinmtp|ex07": 470,
    "afrinmtp|ex08": 470,
    "afrinmtp|ex09": 470,
    "afrinmtp|ex10": 470,
    "VIGHNESH002|ex01": 469,
    "VIGHNESH002|ex02": 469,
    "VIGHNESH002|ex03": 469,
    "VIGHNESH002|ex04": 469,
    "VIGHNESH002|ex05": 469,
    "VIGHNESH002|ex06": 469,
    "VIGHNESH002|ex07": 469,
    "VIGHNESH002|ex08": 469,
    "VIGHNESH002|ex09": 469,
    "VIGHNESH002|ex10": 469,
    "amriththejas|ex01": 468,
    "amriththejas|ex02": 468,
    "amriththejas|ex03": 468,
    "amriththejas|ex04": 468,
    "amriththejas|ex05": 468,
    "amriththejas|ex06": 468,
    "amriththejas|ex07": 468,
    "amriththejas|ex08": 468,
    "amriththejas|ex09": 468,
    "amriththejas|ex10": 468,
    "Vishnureddy910|ex02": 467,
    "Vishnureddy910|ex03": 467,
    "Vishnureddy910|ex04": 467,
    "Vishnureddy910|ex05": 467,
    "Vishnureddy910|ex06": 467,
    "Vishnureddy910|ex07": 467,
    "Vishnureddy910|ex08": 467,
    "Vishnureddy910|ex09": 467,
    "Vishnureddy910|ex10": 467,
    "Adithya-Vipin|ex01": 3,
    "Adithya-Vipin|ex02": 466,
    "Adithya-Vipin|ex03": 466,
    "Adithya-Vipin|ex04": 466,
    "Adithya-Vipin|ex05": 466,
    "Adithya-Vipin|ex06": 466,
    "Adithya-Vipin|ex07": 466,
    "Adithya-Vipin|ex08": 466,
    "Adithya-Vipin|ex09": 466,
    "Adithya-Vipin|ex10": 466,
    "Akif-ka|ex02": 465,
    "Akif-ka|ex03": 465,
    "Akif-ka|ex04": 465,
    "Akif-ka|ex05": 465,
    "Akif-ka|ex06": 465,
    "Akif-ka|ex07": 465,
    "Akif-ka|ex08": 465,
    "Akif-ka|ex09": 465,
    "Akif-ka|ex10": 465,
    "akshay-820|ex02": 464,
    "akshay-820|ex03": 464,
    "akshay-820|ex04": 464,
    "akshay-820|ex05": 464,
    "akshay-820|ex06": 464,
    "akshay-820|ex07": 464,
    "akshay-820|ex08": 464,
    "akshay-820|ex09": 464,
    "akshay-820|ex10": 464,
    "BKSHEERAJ|ex02": 463,
    "BKSHEERAJ|ex03": 463,
    "BKSHEERAJ|ex04": 463,
    "BKSHEERAJ|ex05": 463,
    "BKSHEERAJ|ex06": 463,
    "BKSHEERAJ|ex07": 463,
    "BKSHEERAJ|ex08": 463,
    "BKSHEERAJ|ex09": 463,
    "BKSHEERAJ|ex10": 463,
    "chethanataltaje|ex02": 462,
    "chethanataltaje|ex03": 462,
    "chethanataltaje|ex04": 462,
    "chethanataltaje|ex05": 462,
    "chethanataltaje|ex06": 462,
    "chethanataltaje|ex07": 462,
    "chethanataltaje|ex08": 462,
    "chethanataltaje|ex09": 462,
    "chethanataltaje|ex10": 462,
    "batulhs|ex02": 1,
    "batulhs|ex03": 1,
    "batulhs|ex04": 1,
    "batulhs|ex05": 1,
    "batulhs|ex06": 1,
    "batulhs|ex07": 1,
    "batulhs|ex08": 1,
    "batulhs|ex09": 1,
    "batulhs|ex10": 1
  }
}